pynector/__init__.py
pynector/client.py
pynector/config.py
pynector/errors.py
pynector/concurrency/__init__.py
pynector/concurrency/cancel.py
pynector/concurrency/errors.py
pynector/concurrency/patterns.py
pynector/concurrency/primitives.py
pynector/concurrency/task.py
pynector/telemetry/__init__.py
pynector/telemetry/config.py
pynector/telemetry/context.py
pynector/telemetry/facade.py
pynector/telemetry/logging.py
pynector/telemetry/tracing.py
pynector/transport/__init__.py
pynector/transport/errors.py
pynector/transport/factory.py
pynector/transport/protocol.py
pynector/transport/registry.py
pynector/transport/http/__init__.py
pynector/transport/http/errors.py
pynector/transport/http/factory.py
pynector/transport/http/message.py
pynector/transport/http/transport.py
pynector/transport/message/__init__.py
pynector/transport/message/binary.py
pynector/transport/message/json.py
pynector/transport/sdk/__init__.py
pynector/transport/sdk/adapter.py
pynector/transport/sdk/errors.py
pynector/transport/sdk/factory.py
pynector/transport/sdk/transport.py
pynector-0.1.0.dist-info/METADATA
pynector-0.1.0.dist-info/WHEEL
pynector-0.1.0.dist-info/licenses/LICENSE
pynector-0.1.0.dist-info/RECORD
