Metadata-Version: 2.4
Name: pynector
Version: 0.1.0
Summary: Python Connector Library
Author-email: pynector Team <info@pynector.org>
License: MIT License
License-File: LICENSE
Requires-Python: >=3.9
Requires-Dist: anyio>=4.9.0
Requires-Dist: httpx>=0.27.0
Requires-Dist: pyyaml>=6.0.2
Provides-Extra: all
Requires-Dist: anthropic>=0.8.0; extra == 'all'
Requires-Dist: openai>=1.12.0; extra == 'all'
Requires-Dist: opentelemetry-api>=1.26.0; extra == 'all'
Requires-Dist: opentelemetry-exporter-otlp>=1.32.1; extra == 'all'
Requires-Dist: opentelemetry-exporter-zipkin>=1.11.1; extra == 'all'
Requires-Dist: opentelemetry-sdk>=1.26.0; extra == 'all'
Requires-Dist: structlog>=25.3.0; extra == 'all'
Provides-Extra: observability
Requires-Dist: opentelemetry-api>=1.26.0; extra == 'observability'
Requires-Dist: opentelemetry-sdk>=1.26.0; extra == 'observability'
Requires-Dist: structlog>=25.3.0; extra == 'observability'
Provides-Extra: otlp
Requires-Dist: opentelemetry-exporter-otlp>=1.32.1; extra == 'otlp'
Provides-Extra: sdk
Requires-Dist: anthropic>=0.8.0; extra == 'sdk'
Requires-Dist: openai>=1.12.0; extra == 'sdk'
Provides-Extra: zipkin
Requires-Dist: opentelemetry-exporter-zipkin>=1.11.1; extra == 'zipkin'
